{
	"id": "6cf67755-0918-4c24-bfd4-c395e46d12b0",
	"name": "Poke_PROD",
	"values": [
		{
			"key": "ADD_PROTOCOL",
			"value": "https://",
			"type": "default",
			"enabled": true
		},
		{
			"key": "ADD_URL",
			"value": "pokeapi.co/api/v2/",
			"type": "default",
			"enabled": true
		},
		{
			"key": "POKEMON",
			"value": "charmander",
			"type": "default",
			"enabled": true
		}
	],
	"_postman_variable_scope": "environment",
	"_postman_exported_at": "2023-05-25T16:18:50.915Z",
	"_postman_exported_using": "Postman/10.14.5"
}